streamlit_adjustable_columns/__init__.py
streamlit_adjustable_columns/frontend/package-lock.json
streamlit_adjustable_columns/frontend/package.json
streamlit_adjustable_columns/frontend/webpack.config.js
streamlit_adjustable_columns/frontend/build/index.html
streamlit_adjustable_columns/frontend/build/main.js
streamlit_adjustable_columns/frontend/build/main.js.LICENSE.txt
streamlit_adjustable_columns/frontend/public/index.html
streamlit_adjustable_columns/frontend/src/main.js
tests/__init__.py
tests/conftest.py
tests/e2e_utils.py
tests/test_all_parameters.py
tests/test_basic_columns.py
tests/test_custom_ratios.py
tests/test_e2e_resize.py
tests/test_integration.py
tests/test_labels.py
tests/test_unit.py
tests/test_width_tracking.py
streamlit_adjustable_columns-0.2.1.dist-info/LICENSE
streamlit_adjustable_columns-0.2.1.dist-info/METADATA
streamlit_adjustable_columns-0.2.1.dist-info/WHEEL
streamlit_adjustable_columns-0.2.1.dist-info/top_level.txt
streamlit_adjustable_columns-0.2.1.dist-info/RECORD
