Metadata-Version: 2.1
Name: streamlit-adjustable-columns
Version: 0.2.1
Summary: A Streamlit custom component for creating columns with adjustable widths
Home-page: https://github.com/danieljannai/streamlit-adjustable-columns
Author: Daniel Jannai Epstein
Classifier: Development Status :: 3 - Alpha
Classifier: Intended Audience :: Developers
Classifier: License :: OSI Approved :: MIT License
Classifier: Programming Language :: Python :: 3.9
Classifier: Programming Language :: Python :: 3.10
Classifier: Programming Language :: Python :: 3.11
Requires-Python: >=3.9
License-File: LICENSE
Requires-Dist: streamlit>=1.0.0
Provides-Extra: dev
Requires-Dist: pytest>=7.0.0; extra == "dev"
Requires-Dist: playwright>=1.30.0; extra == "dev"
Requires-Dist: requests>=2.25.0; extra == "dev"
